SloppyV3/common.py
SloppyV3/config.py
SloppyV3/error.py
SloppyV3/excel.py
SloppyV3/json.py
SloppyV3-0.0.0.0.1.dist-info/METADATA
SloppyV3-0.0.0.0.1.dist-info/WHEEL
SloppyV3-0.0.0.0.1.dist-info/top_level.txt
SloppyV3-0.0.0.0.1.dist-info/RECORD
